README.txt
setup.cfg
setup.py
collective/__init__.py
collective.kss.flygui.egg-info/PKG-INFO
collective.kss.flygui.egg-info/SOURCES.txt
collective.kss.flygui.egg-info/dependency_links.txt
collective.kss.flygui.egg-info/entry_points.txt
collective.kss.flygui.egg-info/namespace_packages.txt
collective.kss.flygui.egg-info/not-zip-safe
collective.kss.flygui.egg-info/requires.txt
collective.kss.flygui.egg-info/top_level.txt
collective/kss/__init__.py
collective/kss/flygui/__init__.py
collective/kss/flygui/config.py
collective/kss/flygui/utils.py
collective/kss/flygui/vocabulary.py
collective/kss/flygui/browser/__init__.py
collective/kss/flygui/browser/delete.py
collective/kss/flygui/browser/foldercontents.py
collective/kss/flygui/browser/interfaces.py
collective/kss/flygui/browser/kss_foldercontents.py
collective/kss/flygui/browser/kss_sharing.py
collective/kss/flygui/browser/lock.py
collective/kss/flygui/browser/menu.py
collective/kss/flygui/browser/navigation.py
collective/kss/flygui/browser/sharing.py
collective/kss/flygui/browser/viewlets.py