Metadata-Version: 1.0
Name: collective.kss.flygui
Version: 0.1.0dev
Summary: Imp
Home-page: http://elgring0.wordpress.com
Author: El Gringo
Author-email: christophe.bosse@ingeniweb.com
License: GPL
Keywords: kss folder_contents sharing navigation portlet
Platform: UNKNOWN
Classifier: Programming Language :: Python
Classifier: Topic :: Software Development :: Libraries :: Python Modules
